{"elements":[{"from":[-2.155991960365375,4.023568844405016,-5.909937167935674],"to":[18.790179295987752,25.56087302967768,21.943825703014568],"rotation":{"angle":0,"axis":"y","origin":[8,8,-9.5]},"faces":{"north":{"uv":[0,3.3125,1.59375,4.96875],"texture":"#0"},"east":{"uv":[0,0,2.125,1.65625],"texture":"#0"},"south":{"uv":[3.71875,0,5.3125,1.65625],"texture":"#0"},"west":{"uv":[0,1.65625,2.125,3.3125],"texture":"#0"},"up":{"uv":[3.71875,2.125,2.125,0],"texture":"#0"},"down":{"uv":[3.71875,2.125,2.125,4.25],"texture":"#0"}}}],"textures":{"0":"minecraft:entity/animated/brown_spider/SPIDER"},"display":{"head":{"translation":[0,-6.4,0],"scale":[3.2,3.2,3.2],"rotation":[0,180,0]}},"texture_size":[512,512]}