{
	"format_version": "1.21.11",
	"credit": "Made with Blockbench",
	"texture_size": [128, 48],
	"textures": {
		"0": "item/inventory_trees/spruce_twigs",
		"particle": "item/inventory_trees/spruce_twigs"
	},
	"elements": [
		{
			"from": [-11.04559, 12.87478, 5.02503],
			"to": [6.66007, 12.87478, 14.00869],
			"rotation": {"x": 65.86476, "y": -0.88662, "z": 29.5807, "origin": [6.07122, 5.97219, 5.5103]},
			"faces": {
				"up": {"uv": [9.91406, 6.57789, 12.12727, 3.58333], "texture": "#0"},
				"down": {"uv": [10.1875, 3.56667, 12.40071, 6.56122], "texture": "#0"}
			}
		},
		{
			"from": [-11.10732, 12.22552, 1.39346],
			"to": [6.59834, 12.22552, 8.5455],
			"rotation": {"x": 35.86476, "y": -0.88662, "z": 29.5807, "origin": [6.07122, 5.97219, 5.5103]},
			"faces": {
				"up": {"uv": [10.29688, 9.09811, 11.19088, 15], "rotation": 90, "texture": "#0"},
				"down": {"uv": [11.20651, 9.4, 10.3125, 15.30189], "rotation": 90, "texture": "#0"}
			}
		},
		{
			"from": [-11.1415, 0.28019, 0.50227],
			"to": [6.56416, 0.28019, 9.31149],
			"rotation": {"x": 140.85703, "y": -0.25541, "z": 30.35635, "origin": [6.07122, 5.97219, 5.5103]},
			"faces": {
				"up": {"uv": [10.3125, 9.06667, 11.41365, 14.96855], "rotation": 90, "texture": "#0"},
				"down": {"uv": [11.52147, 8.66478, 10.42031, 14.56667], "rotation": 90, "texture": "#0"}
			}
		},
		{
			"from": [-11.18964, -0.88656, 5.50835],
			"to": [6.60324, -0.88656, 13.61981],
			"rotation": {"x": 107.85703, "y": -0.25541, "z": 30.35635, "origin": [6.07122, 5.97219, 5.5103]},
			"faces": {
				"up": {"uv": [14.5625, 3.23333, 15.57643, 9.16429], "rotation": 90, "texture": "#0"},
				"down": {"uv": [15.3125, 4.225, 14.29857, 10.15596], "rotation": 90, "texture": "#0"}
			}
		},
		{
			"from": [6.59308, -0.83855, 5.55887],
			"to": [11.82628, -0.83855, 13.67033],
			"rotation": {"x": 107.85703, "y": -0.25541, "z": 30.35635, "origin": [6.07122, 5.97219, 5.5103]},
			"faces": {
				"up": {"uv": [14.625, 4.43715, 15.27915, 1.73333], "texture": "#0"},
				"down": {"uv": [14.72085, 2.00451, 15.375, 4.70833], "texture": "#0"}
			}
		},
		{
			"from": [-12.03454, 6.93129, -1.85375],
			"to": [9.59602, 6.93129, 14.63083],
			"rotation": {"x": 87.20755, "y": -4.43231, "z": 3.13953, "origin": [6.07122, 5.97219, 5.5103]},
			"faces": {
				"up": {"uv": [5.9375, 10.50514, 8.64132, 16], "texture": "#0"},
				"down": {"uv": [8.89132, 10.5, 6.1875, 15.99486], "rotation": 180, "texture": "#0"}
			}
		},
		{
			"from": [-1.64747, 6.52918, -0.86543],
			"to": [19.89587, 6.52918, 14.48529],
			"rotation": {"x": 85.26196, "y": 0.78938, "z": 6.88958, "origin": [6.07122, 5.97219, 5.5103]},
			"faces": {
				"up": {"uv": [3.75542, 13.76913, 1.0625, 8.65222], "texture": "#0"},
				"down": {"uv": [3.75542, 8.66667, 1.0625, 13.78357], "texture": "#0"}
			}
		},
		{
			"from": [5.55951, 11.67599, 1.0556],
			"to": [27.71339, 11.67599, 15.0108],
			"rotation": {"x": 41.26535, "y": -0.95415, "z": -7.06318, "origin": [6.07122, 5.97219, 5.5103]},
			"faces": {
				"up": {"uv": [3.76924, 11.34827, 1, 16], "texture": "#0"},
				"down": {"uv": [3.39424, 16, 0.625, 11.34827], "texture": "#0"}
			}
		},
		{
			"from": [5.46645, -0.20295, 1.59919],
			"to": [27.70755, -0.20295, 14.85663],
			"rotation": {"x": 151.26535, "y": -0.95415, "z": -7.06318, "origin": [6.07122, 5.97219, 5.5103]},
			"faces": {
				"up": {"uv": [6.5, 11.91915, 9.28014, 7.5], "texture": "#0"},
				"down": {"uv": [6.5, 7.5, 9.28014, 11.91915], "texture": "#0"}
			}
		},
		{
			"from": [2.4191, 0.04745, 0.89712],
			"to": [12.8855, 0.04745, 8.13638],
			"rotation": {"x": 143.08549, "y": -3.64854, "z": -3.92782, "origin": [6.07122, 5.97219, 5.5103]},
			"faces": {
				"up": {"uv": [10.5625, 11.57975, 11.8708, 9.16667], "texture": "#0"},
				"down": {"uv": [10.5625, 9.16667, 11.8708, 11.57975], "texture": "#0"}
			}
		},
		{
			"from": [2.462, 11.63482, 0.57216],
			"to": [13.01562, 11.63482, 6.93922],
			"rotation": {"x": 42.04713, "y": -2.90616, "z": -3.25674, "origin": [6.07122, 5.97219, 5.5103]},
			"faces": {
				"up": {"uv": [12.825, 6.1, 11.3125, 3.66667], "texture": "#0"},
				"down": {"uv": [12.8817, 3.56667, 11.5625, 5.68902], "texture": "#0"}
			}
		},
		{
			"from": [2.45562, -0.41536, 4.37969],
			"to": [12.92202, -0.41536, 9.00235],
			"rotation": {"x": 110.08549, "y": -3.64854, "z": -3.92782, "origin": [6.07122, 5.97219, 5.5103]},
			"faces": {
				"up": {"uv": [11.0125, 15.23333, 11.675, 11.23333], "rotation": 90, "texture": "#0"},
				"down": {"uv": [11.6125, 15.5, 10.95, 11.5], "rotation": 90, "texture": "#0"}
			}
		},
		{
			"from": [2.50275, 11.63133, 3.94472],
			"to": [13.05637, 11.63133, 8.48016],
			"rotation": {"x": 71.02924, "y": -3.25829, "z": -3.00411, "origin": [6.07122, 5.97219, 5.5103]},
			"faces": {
				"up": {"uv": [12.65, 3.93333, 11.1375, 2.2], "texture": "#0"},
				"down": {"uv": [12.7125, 2.23333, 11.2, 3.96667], "texture": "#0"}
			}
		},
		{
			"from": [-0.94272, 11.71463, 1.20011],
			"to": [8.12816, 11.71463, 4.51447],
			"rotation": {"x": 40.72524, "y": -1.81145, "z": 13.25251, "origin": [6.07122, 5.97219, 5.5103]},
			"faces": {
				"up": {"uv": [2.175, 11.86667, 3.475, 13.13333], "texture": "#0"},
				"down": {"uv": [2.7375, 13.13333, 4.0375, 11.86667], "texture": "#0"}
			}
		},
		{
			"from": [-1.03203, -0.21262, 1.77824],
			"to": [8.12607, -0.21262, 5.00538],
			"rotation": {"x": 152.72524, "y": -1.81145, "z": 13.25251, "origin": [6.07122, 5.97219, 5.5103]},
			"faces": {
				"up": {"uv": [2.9125, 11.7, 4.225, 12.93333], "texture": "#0"},
				"down": {"uv": [3.73125, 10.9, 2.41875, 12.13333], "texture": "#0"}
			}
		},
		{
			"from": [-5.10374, -2.10584, 0.97671],
			"to": [2.30996, -2.10584, 4.02941],
			"rotation": {"x": 153.01907, "y": -2.67708, "z": 35.92919, "origin": [6.07122, 5.97219, 5.5103]},
			"faces": {
				"up": {"uv": [3.7875, 11.53333, 2.725, 12.7], "texture": "#0"},
				"down": {"uv": [2.7875, 10.96667, 3.85, 12.13333], "texture": "#0"}
			}
		},
		{
			"from": [-5.25864, 12.98138, -0.5468],
			"to": [2.41672, 12.98138, 2.85478],
			"rotation": {"x": 43.01907, "y": -2.67708, "z": 35.92919, "origin": [6.07122, 5.97219, 5.5103]},
			"faces": {
				"up": {"uv": [3.6, 11.83333, 2.5, 13.13333], "texture": "#0"},
				"down": {"uv": [3.5375, 13.33333, 2.4375, 12.03333], "texture": "#0"}
			}
		}
	],
	"groups": [
		{
			"name": "group",
			"origin": [6.07122, 5.97219, 5.5103],
			"color": 0,
			"children": [0, 1, 2, 3, 4, 5, 6, 7, 8, 9, 10, 11, 12, 13, 14, 15, 16]
		}
	]
}