{"elements":[{"from":[8.130341240624432,-0.6655420555128941,8.04126085023152],"to":[10.811591240624434,8.161957944487106,10.681260850231524],"rotation":{"angle":0,"axis":"y","origin":[9.130341240624432,3.246332944487108,9.361260850231528]},"faces":{"north":{"uv":[4.1325,1.6325,4.8115,3.8115],"texture":"#4"},"west":{"uv":[4.5075,3.8825,5.1865,6.0615],"texture":"#4"}}}],"textures":{"3":"minecraft:entity/animated/fell_beast/fellbeast_saddle","4":"minecraft:entity/animated/fell_beast/nazgul","5":"minecraft:entity/animated/fell_beast/fell_beast_wings","6":"minecraft:entity/animated/fell_beast/fell_beast"},"display":{"head":{"translation":[0,-6.4,0],"scale":[3.2,3.2,3.2],"rotation":[0,180,0]}},"texture_size":[512,512]}