{"elements":[{"from":[6.134066161313369,7.138915824445071,7.807904624232364],"to":[9.959066161313368,8.713915824445053,12.757904624232367],"rotation":{"angle":0,"axis":"y","origin":[7.997743411313369,8.63666983011925,8.677721353793189]},"faces":{"north":{"uv":[6.4385,11.1885,6.71775,11.3115],"texture":"#6"},"east":{"uv":[6.96975,10.78225,7.3115,10.90525],"texture":"#6"},"south":{"uv":[8.03225,11.1885,8.3115,11.3115],"texture":"#6"},"west":{"uv":[8.84475,11.126,9.1865,11.249],"texture":"#6"},"up":{"uv":[8.84275,7.96775,8.5635,7.626],"texture":"#6"},"down":{"uv":[6.5615,10.84475,6.28225,11.1865],"texture":"#6"}}}],"textures":{"3":"minecraft:entity/animated/fell_beast/fellbeast_saddle","4":"minecraft:entity/animated/fell_beast/nazgul","5":"minecraft:entity/animated/fell_beast/fell_beast_wings","6":"minecraft:entity/animated/fell_beast/fell_beast"},"display":{"head":{"translation":[0,-6.4,0],"scale":[3.2,3.2,3.2],"rotation":[0,180,0]}},"texture_size":[512,512]}