{"elements":[{"from":[8.50525,4.753749999999998,8.0135],"to":[8.50525,7.559500000000001,8.25],"rotation":{"angle":0,"axis":"y","origin":[8,9,7.7124999999999995]},"faces":{"north":{"uv":[0,0,0,6.525000000000006],"texture":"#missing"},"east":{"uv":[14.5,9.5,15.400000000000002,16.025000000000006],"texture":"#1"},"south":{"uv":[0,0,0,6.525000000000006],"texture":"#missing"},"west":{"uv":[14.5,9.5,15.400000000000002,16.025000000000006],"texture":"#1"},"up":{"uv":[0,0,0,0.9000000000000021],"texture":"#missing"},"down":{"uv":[0,0,0,0.9000000000000021],"texture":"#missing"}}}],"textures":{"0":"minecraft:entity/animated/legolas/Legolas","1":"minecraft:entity/animated/legolas/elven_bow","2":"minecraft:entity/animated/legolas/arrow"},"display":{"head":{"translation":[0,-6.4,0],"scale":[3.2,3.2,3.2],"rotation":[0,180,0]}}}