{"elements":[{"from":[6.2967200000000005,8.207722375,6.308375],"to":[9.70328,11.591722374999998,9.692374999999998],"rotation":{"angle":0,"axis":"y","origin":[8,-2.637877625,8.000375]},"faces":{"north":{"uv":[2,2,4,4],"texture":"#0"},"east":{"uv":[0.032,2.032,1.968,3.968],"texture":"#0"},"south":{"uv":[6.032,2.032,7.968,3.968],"texture":"#0"},"west":{"uv":[4.032,2.032,5.968,3.968],"texture":"#0"},"up":{"uv":[3.968,1.968,2.032,0.032],"texture":"#0"},"down":{"uv":[5.968,0.032,4.032,1.968],"texture":"#0"}}},{"from":[6.240889792,8.152286167000003,6.266264792000001],"to":[9.759110208,11.620506583000004,9.770485208],"rotation":{"angle":0,"axis":"y","origin":[8,-1.994513705000001,8.000375]},"faces":{"north":{"uv":[10.032,2.032,11.968,3.968],"texture":"#0"},"east":{"uv":[8.032,2.032,9.968,3.968],"texture":"#0"},"south":{"uv":[14.032,2.032,15.968,3.968],"texture":"#0"},"west":{"uv":[12.032,2.032,13.968,3.968],"texture":"#0"},"up":{"uv":[11.968,1.968,10.032,0.032],"texture":"#0"}}}],"textures":{"0":"minecraft:entity/animated/legolas/Legolas","1":"minecraft:entity/animated/legolas/elven_bow","2":"minecraft:entity/animated/legolas/arrow"},"display":{"head":{"translation":[0,-6.4,0],"scale":[3.2,3.2,3.2],"rotation":[0,180,0]}}}