{"elements":[{"from":[6,8,7],"to":[10,14,9],"rotation":{"angle":0,"axis":"y","origin":[8,2,8]},"faces":{"north":{"uv":[5.008,5.008,6.992,7.992],"texture":"#0"},"east":{"uv":[4.032,5.032,4.968,7.968],"texture":"#0"},"south":{"uv":[8.032,5.032,9.968,7.968],"texture":"#0"},"west":{"uv":[7.032,5.032,7.968,7.968],"texture":"#0"},"up":{"uv":[6.968,4.968,5.032,4.032],"texture":"#0"},"down":{"uv":[8.968,4.032,7.032,4.968],"texture":"#0"}}},{"from":[5.875,7.875,6.875],"to":[10.125,14.125,9.125],"rotation":{"angle":0,"axis":"y","origin":[8,2,8]},"faces":{"north":{"uv":[5.032,9.032,6.968,11.967999999999998],"texture":"#0"},"east":{"uv":[4.032,9.032,4.968,11.967999999999998],"texture":"#0"},"south":{"uv":[8.032,9.032,9.968,11.967999999999998],"texture":"#0"},"west":{"uv":[7.032,9.032,7.968,11.967999999999998],"texture":"#0"},"up":{"uv":[6.968,8.968,5.032,8.032],"texture":"#0"},"down":{"uv":[8.968,8.032,7.032,8.968],"texture":"#0"}}}],"textures":{"0":"minecraft:entity/animated/gandalf/Gandalf","1":"minecraft:entity/animated/gandalf/gandalf_sword_blade","2":"minecraft:entity/animated/gandalf/gandalf_staff","3":"minecraft:entity/animated/gandalf/gandalf_sword","4":"minecraft:entity/animated/gandalf/gandalf_hat"},"display":{"head":{"translation":[0,-6.4,0],"scale":[3.2,3.2,3.2],"rotation":[0,180,0]}},"texture_size":[48,48]}