{"textures":{"4":"modelengine:entity/misty_mts","particle":"#4"},"elements":[{"from":[-10.4,8.0,-1.25],"to":[8.0,8.01953,17.15],"faces":{"up":{"uv":[11.935136,15.913513,7.9567566,11.935136],"tintindex":0,"rotation":0,"texture":"#4"},"down":{"uv":[11.935136,11.935136,7.9567566,15.913513],"tintindex":0,"rotation":0,"texture":"#4"}}}],"display":{"head":{"rotation":[0.0,0.0,0.0]},"firstperson_righthand":{"rotation":[0.0,0.0,0.0]},"thirdperson_lefthand":{"rotation":[0.0,-0.0,-0.0]},"firstperson_lefthand":{"rotation":[0.0,-0.0,-0.0]},"fixed":{"rotation":[0.0,0.0,0.0]},"ground":{"rotation":[0.0,0.0,0.0]},"thirdperson_righthand":{"rotation":[0.0,0.0,0.0]},"gui":{"rotation":[-150.0,-45.0,180.0]}}}