{"elements":[{"from":[7,5.290728352484907,7.036900237754223],"to":[8.75,8.290728352484908,8.786900237754223],"rotation":{"angle":0,"axis":"y","origin":[5,-0.5,8]},"faces":{"north":{"uv":[11.032,6.508,11.742,7.968],"texture":"#5"},"east":{"uv":[10.008,6.508,10.992,7.992],"texture":"#5"},"south":{"uv":[13.258,6.508,13.968,7.968],"texture":"#5"},"west":{"uv":[12.032,6.508,12.742,7.968],"texture":"#5"},"up":{"uv":[11.032,4.032,11.742,4.742],"texture":"#5"},"down":{"uv":[12.008,4.008,12.992,4.992],"texture":"#5"}}},{"from":[6.9350000000000005,5.274577832340469,6.962868794133584],"to":[8.815,8.306077832340469,8.842868794133583],"rotation":{"angle":0,"axis":"y","origin":[5.1725,-0.2479221676595298,8.020368794133583]},"faces":{"north":{"uv":[9.008,14.508,9.992,15.992],"texture":"#5"},"east":{"uv":[8.008,14.508,8.992,15.992],"texture":"#5"},"south":{"uv":[11.125,14.508,11.992,15.992],"texture":"#5"},"west":{"uv":[10.508,14.508,11.218,15.968],"texture":"#5"},"up":{"uv":[9.258,13.875,10.065,14.69],"texture":"#5"},"down":{"uv":[10.008,12.008,10.992,12.992],"texture":"#5"}}}],"textures":{"0":"minecraft:entity/animated/boromir/boromir_shield","1":"minecraft:entity/animated/boromir/boromir_horn","3":"minecraft:entity/animated/boromir/boromir_sword","4":"minecraft:entity/animated/boromir/boromir_sword_blade","5":"minecraft:entity/animated/boromir/Boromir","6":"minecraft:entity/animated/boromir/arrow"},"display":{"head":{"translation":[0,-6.4,0],"scale":[3.2,3.2,3.2],"rotation":[0,180,0]}},"texture_size":[64,64]}