{"overrides":[{"predicate":{"custom_model_data":2},"model":"modelengine:book_and_map/bone3"},{"predicate":{"custom_model_data":17},"model":"modelengine:book_and_map/bone6"},{"predicate":{"custom_model_data":45},"model":"modelengine:book_and_map/book"},{"predicate":{"custom_model_data":46},"model":"modelengine:book_and_map/page_8"},{"predicate":{"custom_model_data":57},"model":"modelengine:book_and_map/bone13"},{"predicate":{"custom_model_data":78},"model":"modelengine:book_and_map/bone5"},{"predicate":{"custom_model_data":80},"model":"modelengine:book_and_map/bone4"},{"predicate":{"custom_model_data":81},"model":"modelengine:book_and_map/bone15"},{"predicate":{"custom_model_data":82},"model":"modelengine:book_and_map/back_cover"},{"predicate":{"custom_model_data":83},"model":"modelengine:book_and_map/page_1"},{"predicate":{"custom_model_data":84},"model":"modelengine:book_and_map/page_6"},{"predicate":{"custom_model_data":113},"model":"modelengine:book_and_map/bone8"},{"predicate":{"custom_model_data":116},"model":"modelengine:book_and_map/bone"},{"predicate":{"custom_model_data":117},"model":"modelengine:book_and_map/front_cover"},{"predicate":{"custom_model_data":118},"model":"modelengine:book_and_map/page_4"},{"predicate":{"custom_model_data":119},"model":"modelengine:book_and_map/page_7"},{"predicate":{"custom_model_data":144},"model":"modelengine:book_and_map/bone10"},{"predicate":{"custom_model_data":148},"model":"modelengine:book_and_map/bone16"},{"predicate":{"custom_model_data":149},"model":"modelengine:book_and_map/page_3"},{"predicate":{"custom_model_data":150},"model":"modelengine:book_and_map/page_5"},{"predicate":{"custom_model_data":162},"model":"modelengine:book_and_map/bone14"},{"predicate":{"custom_model_data":164},"model":"modelengine:book_and_map/bone11"},{"predicate":{"custom_model_data":172},"model":"modelengine:book_and_map/bone2"},{"predicate":{"custom_model_data":178},"model":"modelengine:book_and_map/bone7"},{"predicate":{"custom_model_data":183},"model":"modelengine:book_and_map/page_2"},{"predicate":{"custom_model_data":196},"model":"modelengine:book_and_map/bone12"},{"predicate":{"custom_model_data":197},"model":"modelengine:book_and_map/bone9"}],"parent":"minecraft:item/generated","textures":{"layer0":"minecraft:item/leather_horse_armor"}}