{
	"textures": {
		"1": "minecraft:block/supported_info_paper"
	},
	"elements": [
		{
			"from": [4.99, 6.5, 4.99],
			"to": [11.01, 9.5, 11.01],
			"light_emission": 0,
			"faces": {
				"north": {
					"uv": [0, 0, 16, 6],
					"texture": "#1"
				},
				"east": {
					"uv": [0, 6.98, 16, 12.98],
					"texture": "#1"
				},
				"south": {
					"uv": [0, 6.98, 16, 12.98],
					"texture": "#1"
				},
				"west": {
					"uv": [0, 6.98, 16, 12.98],
					"texture": "#1"
				},
				"up": {
					"uv": [0, 6.98, 16, 16],
					"texture": "#1"
				},
				"down": {
					"uv": [0, 6.98, 16, 16],
					"texture": "#1"
				}
			}
		}
	],
	"display": {
		"fixed": {
			"rotation": [-90, 0, 0],
			"translation": [0, 0, -9.375],
			"scale": [2.5, 2.5, 2.5]
		}
	}
}